LICENSE
MANIFEST.in
README.md
setup.py
postgres_audit_triggers/__init__.py
postgres_audit_triggers/apps.py
postgres_audit_triggers/decorators.py
postgres_audit_triggers/middleware.py
postgres_audit_triggers/models.py
postgres_audit_triggers/operations.py
postgres_audit_triggers/serializers.py
postgres_audit_triggers.egg-info/PKG-INFO
postgres_audit_triggers.egg-info/SOURCES.txt
postgres_audit_triggers.egg-info/dependency_links.txt
postgres_audit_triggers.egg-info/top_level.txt
postgres_audit_triggers/management/__init__.py
postgres_audit_triggers/management/commands/__init__.py
postgres_audit_triggers/management/commands/makemigrations.py
postgres_audit_triggers/migrations/0001_initial.py
postgres_audit_triggers/migrations/0002_audit_metadata.py
postgres_audit_triggers/migrations/0003_metadata_tweak.py
postgres_audit_triggers/migrations/0004_indexes.py
postgres_audit_triggers/migrations/0005_indexes.py
postgres_audit_triggers/migrations/__init__.py
postgres_audit_triggers/sql/audit_0001.sql
postgres_audit_triggers/sql/audit_0002.sql
postgres_audit_triggers/sql/audit_0003.sql