Metadata-Version: 2.1
Name: postgres-audit-triggers
Version: 1.2.1
Summary: Postgres audit triggers for Django
Home-page: https://github.com/carta/postgres_audit_triggers
Author: Jared Hobbs
Author-email: jared.hobbs@carta.com
License: MIT
Keywords: django,postgres,audit,triggers
Platform: UNKNOWN
Classifier: Development Status :: 5 - Production/Stable
Classifier: Environment :: Console
Classifier: Intended Audience :: Developers
Classifier: License :: OSI Approved :: MIT License
Classifier: Operating System :: OS Independent
Classifier: Programming Language :: Python :: 3.5
Classifier: Topic :: Text Processing
Classifier: Topic :: Utilities
Requires-Python: >=3.5
